pp_up/__init__.py
pp_up/__main__.py
pp_up/func.py
pp_up-0.1.0.dist-info/LICENSE
pp_up-0.1.0.dist-info/METADATA
pp_up-0.1.0.dist-info/WHEEL
pp_up-0.1.0.dist-info/top_level.txt
pp_up-0.1.0.dist-info/RECORD
