Metadata-Version: 2.1
Name: pp-up
Version: 0.1.0
Summary: Update pypi dependencies
Home-page: https://github.com/jbwdevries/pp-up
Author: Johan B.W. de Vries
License: UNKNOWN
Project-URL: Bug Tracker, https://github.com/jbwdevries/pp-up/issues
Project-URL: Source Code, https://github.com/jbwdevries/pp-up
Platform: UNKNOWN
Classifier: License :: OSI Approved :: MIT License
Classifier: Programming Language :: Python :: 3
Classifier: Operating System :: OS Independent
Requires-Python: >=3.6
Requires-Dist: requests
Provides-Extra: develop
Requires-Dist: mypy (==0.770) ; extra == 'develop'
Requires-Dist: pylint (==2.4.4) ; extra == 'develop'
Requires-Dist: setuptools (==46.1.3) ; extra == 'develop'
Requires-Dist: twine (==3.1.1) ; extra == 'develop'
